LICENSE
MANIFEST.in
README.md
setup.py
django_weapp_auth.egg-info/PKG-INFO
django_weapp_auth.egg-info/SOURCES.txt
django_weapp_auth.egg-info/dependency_links.txt
django_weapp_auth.egg-info/requires.txt
django_weapp_auth.egg-info/top_level.txt
weapp_auth/__init__.py
weapp_auth/admin.py
weapp_auth/apps.py
weapp_auth/models.py
weapp_auth/tests.py
weapp_auth/urls.py
weapp_auth/views.py
weapp_auth/authenticator/OpenIdAuthenticator.py
weapp_auth/authenticator/__init__.py
weapp_auth/migrations/0001_initial.py
weapp_auth/migrations/__init__.py
weapp_auth/wechat/WXBizDataCrypt.py
weapp_auth/wechat/WeChatUserHelper.py
weapp_auth/wechat/WechatSignHelper.py
weapp_auth/wechat/__init__.py