Metadata-Version: 2.1
Name: django-weapp-auth
Version: 1.0.6
Summary: A helper Django app that handles wechat mini program login and user info updating logic
Home-page: https://blog.mimimi.fun/
Author: Meowzz95
Author-email: info@mimimi.fun
License: BSD License
Platform: UNKNOWN
Classifier: Environment :: Web Environment
Classifier: Framework :: Django
Classifier: Framework :: Django :: 2.2
Classifier: Intended Audience :: Developers
Classifier: License :: OSI Approved :: BSD License
Classifier: Operating System :: OS Independent
Classifier: Programming Language :: Python
Classifier: Programming Language :: Python :: 3.5
Classifier: Programming Language :: Python :: 3.6
Classifier: Topic :: Internet :: WWW/HTTP
Classifier: Topic :: Internet :: WWW/HTTP :: Dynamic Content
